google/__init__.py
google/google.py
google/modules/__init__.py
google/modules/calculator.py
google/modules/currency.py
google/modules/images.py
google/modules/shopping_search.py
google/modules/standard_search.py
google/modules/utils.py
google/tests/__init__.py
google/tests/test_google.py
google/tests/test_utils.py
Google_Search_API-1.1.14.dist-info/METADATA
Google_Search_API-1.1.14.dist-info/WHEEL
Google_Search_API-1.1.14.dist-info/top_level.txt
Google_Search_API-1.1.14.dist-info/RECORD
