Metadata-Version: 1.2
Name: Google-Search-API
Version: 1.1.14
Summary: Search in google
Home-page: https://github.com/abenassi/Google-Search-API
Author: Anthony Casagrande, Agustin Benassi
Author-email: birdapi@gmail.com, agusbenassi@gmail.com
Maintainer: Agustin Benassi
Maintainer-email: agusbenassi@gmail.com
License: MIT
Keywords: google search images api
Platform: UNKNOWN
Classifier: Development Status :: 3 - Alpha
Classifier: Intended Audience :: Developers
Classifier: Natural Language :: English
Classifier: Programming Language :: Python :: 3
Classifier: Programming Language :: Python :: 3.5
Classifier: Programming Language :: Python :: 3.6
Classifier: Programming Language :: Python :: 3.7
